emloop/__init__.py
emloop/api.py
emloop/constants.py
emloop/entry_point.py
emloop/main_loop.py
emloop/types.py
emloop/cli/__init__.py
emloop/cli/args.py
emloop/cli/dataset.py
emloop/cli/eval.py
emloop/cli/grid_search.py
emloop/cli/ls.py
emloop/cli/prune.py
emloop/cli/resume.py
emloop/cli/train.py
emloop/cli/util.py
emloop/datasets/__init__.py
emloop/datasets/abstract_dataset.py
emloop/datasets/base_dataset.py
emloop/datasets/downloadable_dataset.py
emloop/datasets/stream_wrapper.py
emloop/hooks/__init__.py
emloop/hooks/abstract_hook.py
emloop/hooks/accumulate_variables.py
emloop/hooks/benchmark.py
emloop/hooks/check.py
emloop/hooks/classification_metrics.py
emloop/hooks/compute_stats.py
emloop/hooks/every_n_epoch.py
emloop/hooks/flatten.py
emloop/hooks/log_dir.py
emloop/hooks/log_profile.py
emloop/hooks/log_variables.py
emloop/hooks/logits_to_csv.py
emloop/hooks/on_plateau.py
emloop/hooks/plot_lines.py
emloop/hooks/save.py
emloop/hooks/save_cm.py
emloop/hooks/save_file.py
emloop/hooks/save_masks.py
emloop/hooks/sequence_to_csv.py
emloop/hooks/show_progress.py
emloop/hooks/stop_after.py
emloop/hooks/stop_on_nan.py
emloop/hooks/stop_on_plateau.py
emloop/hooks/training_trace.py
emloop/hooks/write_csv.py
emloop/models/__init__.py
emloop/models/abstract_model.py
emloop/models/ensemble.py
emloop/models/sequence.py
emloop/tests/__init__.py
emloop/tests/api_test.py
emloop/tests/conftest.py
emloop/tests/main_loop_test.py
emloop/utils/__init__.py
emloop/utils/config.py
emloop/utils/confusion_matrix.py
emloop/utils/download.py
emloop/utils/misc.py
emloop/utils/names.py
emloop/utils/profile.py
emloop/utils/reflection.py
emloop/utils/yaml.py
emloop-0.2.1.dist-info/LICENSE
emloop-0.2.1.dist-info/METADATA
emloop-0.2.1.dist-info/WHEEL
emloop-0.2.1.dist-info/entry_points.txt
emloop-0.2.1.dist-info/top_level.txt
emloop-0.2.1.dist-info/RECORD
